streamlit_iframe/__init__.py
streamlit_iframe/version.py
streamlit_iframe/frontend/build/asset-manifest.json
streamlit_iframe/frontend/build/index.html
streamlit_iframe/frontend/build/static/js/main.199cde9b.js
streamlit_iframe/frontend/build/static/js/main.199cde9b.js.LICENSE.txt
streamlit_iframe/frontend/build/static/js/main.199cde9b.js.map
streamlit_iframe-0.1.0.dist-info/METADATA
streamlit_iframe-0.1.0.dist-info/WHEEL
streamlit_iframe-0.1.0.dist-info/top_level.txt
streamlit_iframe-0.1.0.dist-info/RECORD
