Metadata-Version: 2.1
Name: streamlit_iframe
Version: 0.1.0
Summary: Render an HTML iframe within a Streamlit app
Home-page: https://github.com/itdsntwork/streamlit-iframe
Author: Manos Nikakis
Author-email: scrtmanos@gmail.com
Classifier: Programming Language :: Python :: 3
Classifier: Operating System :: OS Independent
Requires-Python: >=3.7
Requires-Dist: streamlit>=0.63
